screwduplicates/README.MD
screwduplicates/__init__.py
screwduplicates/requirements.txt
screwduplicates/thirdparty.json
screwduplicates-0.11.dist-info/LICENSE.rst
screwduplicates-0.11.dist-info/METADATA
screwduplicates-0.11.dist-info/WHEEL
screwduplicates-0.11.dist-info/top_level.txt
screwduplicates-0.11.dist-info/RECORD
