Metadata-Version: 2.1
Name: screwduplicates
Version: 0.11
Summary: provides a simple and efficient way to remove duplicates from an iterable (even with unhashable elements, optional order preservation)
Home-page: https://github.com/hansalemaos/screwduplicates
Author: Johannes Fischer
Author-email: aulasparticularesdealemaosp@gmail.com
License: MIT
Keywords: remove,duplicates
Classifier: Development Status :: 4 - Beta
Classifier: Programming Language :: Python :: 3 :: Only
Classifier: Programming Language :: Python :: 3.10
Classifier: Topic :: Software Development :: Libraries :: Python Modules
Classifier: Topic :: Utilities
License-File: LICENSE.rst
